sysaidmin/__init__.py
sysaidmin/cli.py
sysaidmin-0.2.5.dist-info/METADATA
sysaidmin-0.2.5.dist-info/WHEEL
sysaidmin-0.2.5.dist-info/entry_points.txt
sysaidmin-0.2.5.dist-info/licenses/LICENSE
sysaidmin-0.2.5.dist-info/RECORD
