Metadata-Version: 2.4
Name: sysaidmin
Version: 0.2.5
Summary: An LLM-powered sysadmin.
Project-URL: repository, https://github.com/skorokithakis/sysaidmin/
Author-email: Stavros Korokithakis <hi@stavros.io>
License-Expression: AGPL-3.0-or-later
License-File: LICENSE
Requires-Python: >=3.9
Requires-Dist: openai-agents>=0.0.11
